digitalocean_inventory/__init__.py
digitalocean_inventory/__main__.py
digitalocean_inventory/exceptions.py
digitalocean_inventory/formatter.py
digitalocean_inventory/inventory.py
digitalocean_inventory/manager.py
digitalocean_inventory-1.1.0.dist-info/LICENSE.md
digitalocean_inventory-1.1.0.dist-info/METADATA
digitalocean_inventory-1.1.0.dist-info/WHEEL
digitalocean_inventory-1.1.0.dist-info/entry_points.txt
digitalocean_inventory-1.1.0.dist-info/top_level.txt
digitalocean_inventory-1.1.0.dist-info/RECORD
