Metadata-Version: 2.1
Name: digitalocean-inventory
Version: 1.1.0
Summary: An ansible dynamic inventory for DigitalOcean
Home-page: https://github.com/JoelLefkowitz/digitalocean-inventory
Author: Joel Lefkowitz
Author-email: joellefkowitz@hotmail.com
License: UNKNOWN
Platform: UNKNOWN
Requires-Python: >=3.6
Requires-Dist: dataclasses
Requires-Dist: safe-environ
Requires-Dist: python-digitalocean
Provides-Extra: dist
Requires-Dist: wheel ; extra == 'dist'
Requires-Dist: twine ; extra == 'dist'
Requires-Dist: bump2version ; extra == 'dist'
Provides-Extra: docs
Requires-Dist: sphinx ; extra == 'docs'
Requires-Dist: pypandoc ; extra == 'docs'
Requires-Dist: sphinxcontrib.apidoc ; extra == 'docs'
Requires-Dist: sphinxcontrib.pandoc-markdown ; extra == 'docs'
Requires-Dist: sphinx-autodoc-annotation ; extra == 'docs'
Requires-Dist: yummy-sphinx-theme ; extra == 'docs'
Provides-Extra: tests
Requires-Dist: pytest ; extra == 'tests'
Requires-Dist: pytest-cov ; extra == 'tests'
Requires-Dist: pytest-html ; extra == 'tests'
Requires-Dist: pytest-sugar ; extra == 'tests'
Requires-Dist: pytest-bdd ; extra == 'tests'
Requires-Dist: pytest-watch ; extra == 'tests'
